quantalogic_toolbox/__init__.py
quantalogic_toolbox/tool.py
quantalogic_toolbox-0.11.0.dist-info/METADATA
quantalogic_toolbox-0.11.0.dist-info/WHEEL
quantalogic_toolbox-0.11.0.dist-info/RECORD
