Metadata-Version: 2.3
Name: quantalogic-toolbox
Version: 0.11.0
Summary: Reusable tool argument and base tool classes extracted from quantalogic.
License: MIT
Author: Raphael Mansuy
Author-email: raphae.mansuy@quantalogic.app
Requires-Python: >=3.9,<4.0
Classifier: License :: OSI Approved :: MIT License
Classifier: Programming Language :: Python :: 3
Classifier: Programming Language :: Python :: 3.9
Classifier: Programming Language :: Python :: 3.10
Classifier: Programming Language :: Python :: 3.11
Classifier: Programming Language :: Python :: 3.12
Classifier: Programming Language :: Python :: 3.13
Requires-Dist: docstring-parser (>=0.15,<1.0)
Requires-Dist: pydantic (>=1.10,<3.0)
